native/xrp/_init_robotpy_native_xrp.py
native/xrp/robotpy-native-xrp.pc
native/xrp/include/frc/xrp/XRPGyro.h
native/xrp/include/frc/xrp/XRPMotor.h
native/xrp/include/frc/xrp/XRPOnBoardIO.h
native/xrp/include/frc/xrp/XRPRangefinder.h
native/xrp/include/frc/xrp/XRPReflectanceSensor.h
native/xrp/include/frc/xrp/XRPServo.h
native/xrp/lib/libxrpVendordep.so
robotpy_native_xrp-2026.2.1.dist-info/METADATA
robotpy_native_xrp-2026.2.1.dist-info/WHEEL
robotpy_native_xrp-2026.2.1.dist-info/entry_points.txt
robotpy_native_xrp-2026.2.1.dist-info/RECORD
