Metadata-Version: 2.4
Name: robotpy-native-xrp
Version: 2026.2.1
Summary: WPILib XRP vendor library
License-Expression: BSD-3-Clause
Requires-Dist: robotpy-native-wpilib==2026.2.1
